{
  "appId": "app.tissini.webview_tissini", 
  "appName": "webview_tissini",
  "bundledWebRuntime": false,
  "npmClient": "npm",
  "webDir": "dist",
  "plugins": {
    "SplashScreen": {
      "launchShowDuration": 0,
      "launchAutoHide": false,
      "backgroundColor": "#fff",
      "androidSplashResourceName": "splash",
      "androidScaleType": "CENTER_CROP",
      "androidSpinnerStyle": "large",
      "iosSpinnerStyle": "small",
      "spinnerColor": "#c92a75",
      "showSpinner": true,
      "splashFullScreen": true,
      "splashImmersive": true
    },
    
    "PushNotifications": {
      "presentationOptions": ["badge", "sound", "alert"]
    },
    "LocalNotifications": {
      "smallIcon": "res://ic_launcher_round",
      "iconColor": "#FF4EF2"
    }
  },
  "cordova": {}
}
